[
    { "value": "boxe-anglaise", "label": "Boxe Anglaise" },
    { "value": "boxe-francaise", "label": "Boxe Française (Savate)" },
    { "value": "boxe-thai", "label": "Boxe Thaïlandaise (Muay Thaï)" },
    { "value": "kickboxing", "label": "Kickboxing" },
    { "value": "full-contact", "label": "Full Contact" },
    { "value": "mma", "label": "Arts Martiaux Mixtes (MMA)" },
    { "value": "karate", "label": "Karaté" },
    { "value": "taekwondo", "label": "Taekwondo" },
    { "value": "judo", "label": "Judo" },
    { "value": "brazilian-jiu-jitsu", "label": "Jiu-Jitsu Brésilien" },
    { "value": "lutte", "label": "Lutte" },
    { "value": "lutte-greco-romaine", "label": "Lutte Gréco-Romaine" },
    { "value": "sambo", "label": "Sambo" },
    { "value": "kung-fu", "label": "Kung-Fu" },
    { "value": "aikido", "label": "Aïkido" },
    { "value": "kendo", "label": "Kendo" },
    { "value": "savate", "label": "Savate" },
    { "value": "escrime", "label": "Escrime" },
    { "value": "sumo", "label": "Sumo" },
    { "value": "capoeira", "label": "Capoeira" },
    { "value": "krav-maga", "label": "Krav Maga" },
    { "value": "jeet-kune-do", "label": "Jeet Kune Do" }
]
